my_joke/__init__.py
my_joke/first_joke.py
my_joke/second_joke.py
my_good_jokes-0.1.dist-info/METADATA
my_good_jokes-0.1.dist-info/WHEEL
my_good_jokes-0.1.dist-info/top_level.txt
my_good_jokes-0.1.dist-info/RECORD
