Metadata-Version: 2.1
Name: my-good-jokes
Version: 0.1
Summary: no description available
Home-page: UNKNOWN
Author: UNKNOWN
Author-email: UNKNOWN
License: MIT
Platform: UNKNOWN
